<orders>
  <order>
    <orderID>1</orderID>
    <customer>Pentti</customer>
    <address>Pentinkatu 1</address>
    <item1>
      <name>Nappi</name>
      <productID>1</productID>
    </item1>
    <item2>
      <name>Lanka</name>
      <productID>2</productID>
    </item2>
    <item3>
      <name>Ohje</name>
      <productID>3</productID>
    </item3>
  </order>
  <order>
    <orderID>2</orderID>
    <customer>Sari</customer>
    <address>Sarinkatu 1</address>
    <item1>
      <name>Auto</name>
      <productID>4</productID>
    </item1>
    <item2>
      <name>Mopo</name>
      <productID>5</productID>
    </item2>
    <item3>
      <name>Kevari</name>
      <productID>6</productID>
    </item3>
    <item4>
      <name>Suklaalevy</name>
      <productID>7</productID>
    </item4>
  </order>
  <order>
    <orderID>3</orderID>
    <customer>Jouko</customer>
    <address>Joukonkatu 1</address>
    <item1>
      <name>Tietokone</name>
      <productID>8</productID>
    </item1>
    <item2>
      <name>Hiiri</name>
      <productID>9</productID>
    </item2>
  </order>
  <order>
    <orderID>4</orderID>
    <customer>Taina</customer>
    <address>Tainankatu 1</address>
    <item1>
      <name>Johto</name>
      <productID>10</productID>
    </item1>
    <item2>
      <name>Nappi</name>
      <productID>1</productID>
    </item2>
    <item3>
      <name>Lanka</name>
      <productID>2</productID>
    </item3>
    <item4>
      <name>Ohje</name>
      <productID>3</productID>
    </item4>
    <item5>
      <name>Kevari</name>
      <productID>6</productID>
    </item5>
  </order>
  <order>
    <orderID></orderID>
    <customer></customer>
    <address></address>
    <item1>
      <name></name>
      <productID></productID>
    </item1>
    <item2>
      <name></name>
      <productID></productID>
    </item2>
    <item3>
      <name></name>
      <productID></productID>
    </item3>
    <item4>
      <name></name>
      <productID></productID>
    </item4>
    <item5>
      <name></name>
      <productID></productID>
    </item5>
    <item6>
      <name></name>
      <productID></productID>
    </item6>
  </order>
</orders>